aiforce/__init__.py
aiforce/_nbdev.py
aiforce/annotation_converter.py
aiforce/annotation_viewer.py
aiforce/category_tools.py
aiforce/core.py
aiforce/dataset_generator.py
aiforce/annotation/__init__.py
aiforce/annotation/core.py
aiforce/annotation/folder_category_adapter.py
aiforce/annotation/multi_category_adapter.py
aiforce/annotation/via_adapter.py
aiforce/annotation/yolo_adapter.py
aiforce/dataset/__init__.py
aiforce/dataset/core.py
aiforce/dataset/image_classification.py
aiforce/dataset/image_object_detection.py
aiforce/dataset/image_segmentation.py
aiforce/dataset/type.py
aiforce/evaluation/__init__.py
aiforce/evaluation/core.py
aiforce/image/__init__.py
aiforce/image/color_palette.py
aiforce/image/opencv_tools.py
aiforce/image/pillow_tools.py
aiforce/image/tools.py
aiforce/io/__init__.py
aiforce/io/core.py
aiforce/tensorflow/__init__.py
aiforce/tensorflow/tflite_converter.py
aiforce/tensorflow/tflite_metadata.py
aiforce/tensorflow/tfrecord_builder.py
aiforce/tools/__init__.py
aiforce/tools/check_double_images.py
aiforce/tools/downloader.py
aiforce/tools/image_size_calculator.py
aiforce-0.0.2.dist-info/LICENSE
aiforce-0.0.2.dist-info/METADATA
aiforce-0.0.2.dist-info/WHEEL
aiforce-0.0.2.dist-info/entry_points.txt
aiforce-0.0.2.dist-info/top_level.txt
aiforce-0.0.2.dist-info/RECORD
